{
    "repository": "DenverCoder1/github-readme-youtube-cards",
    "stars": 93,
    "language": "python",
    "size": 398,
    "clone_url": "https://github.com/DenverCoder1/github-readme-youtube-cards.git",
    "timestamp": "2023-06-16T15:50:06.955899Z",
    "clone_success": true,
    "number of actions": 0,
    "number_of_test_actions": 0,
    "actions_successful": false,
    "number_of_actions": 4,
    "actions_build_tools": [
        "unknown",
        "unknown",
        "unknown",
        "unknown"
    ],
    "actions_test_build_tools": []
}