{
    "repository": "home-assistant-ecosystem/home-assistant-cli",
    "stars": 364,
    "language": "python",
    "size": 565,
    "clone_url": "https://github.com/home-assistant-ecosystem/home-assistant-cli.git",
    "timestamp": "2023-06-16T11:58:58.984410Z",
    "clone_success": true,
    "number of actions": 0,
    "number_of_test_actions": 1,
    "actions_successful": false,
    "number_of_actions": 1,
    "actions_build_tools": [
        "pytest"
    ],
    "actions_test_build_tools": [
        "pytest"
    ],
    "actions_tests": []
}